hamlet/__about__.py
hamlet/__init__.py
hamlet/__main__.py
hamlet/__version__.py
hamlet/loggers.py
hamlet/backend/__init__.py
hamlet/backend/cmdb/__init__.py
hamlet/backend/cmdb/save/__init__.py
hamlet/backend/common/__init__.py
hamlet/backend/common/aws_credentials_session.py
hamlet/backend/common/aws_ssm_session.py
hamlet/backend/common/context.py
hamlet/backend/common/exceptions.py
hamlet/backend/common/fsutils.py
hamlet/backend/common/http_client.py
hamlet/backend/common/runner.py
hamlet/backend/common/shell_vars_to_json.py
hamlet/backend/common/shell_vars_to_json.sh
hamlet/backend/common/utilities.py
hamlet/backend/container_registry/__init__.py
hamlet/backend/contract/__init__.py
hamlet/backend/contract/tasks/__init__.py
hamlet/backend/contract/tasks/exceptions.py
hamlet/backend/contract/tasks/aws_cfn_changeset_replacements/__init__.py
hamlet/backend/contract/tasks/aws_cfn_create_changeset/__init__.py
hamlet/backend/contract/tasks/aws_cfn_delete_stack/__init__.py
hamlet/backend/contract/tasks/aws_cfn_execute_changeset/__init__.py
hamlet/backend/contract/tasks/aws_cli_bash_script/__init__.py
hamlet/backend/contract/tasks/aws_ec2_select_instance/__init__.py
hamlet/backend/contract/tasks/aws_ecr_docker_login/__init__.py
hamlet/backend/contract/tasks/aws_ecs_run_command/__init__.py
hamlet/backend/contract/tasks/aws_ecs_run_task/__init__.py
hamlet/backend/contract/tasks/aws_ecs_select_task/__init__.py
hamlet/backend/contract/tasks/aws_kms_decrypt_ciphertext/__init__.py
hamlet/backend/contract/tasks/aws_kms_encrypt_value/__init__.py
hamlet/backend/contract/tasks/aws_lambda_invoke_function/__init__.py
hamlet/backend/contract/tasks/aws_rds_create_snapshot/__init__.py
hamlet/backend/contract/tasks/aws_s3_download_bucket/__init__.py
hamlet/backend/contract/tasks/aws_s3_download_object/__init__.py
hamlet/backend/contract/tasks/aws_s3_empty_bucket/__init__.py
hamlet/backend/contract/tasks/aws_s3_upload_object/__init__.py
hamlet-10.0.1.dist-info/LICENSE
hamlet-10.0.1.dist-info/METADATA
hamlet-10.0.1.dist-info/WHEEL
hamlet-10.0.1.dist-info/entry_points.txt
hamlet-10.0.1.dist-info/top_level.txt
hamlet-10.0.1.dist-info/RECORD
