Metadata-Version: 2.1
Name: hamlet
Version: 10.0.1
Summary: Building your infrastructure
Home-page: https://hamlet.io
Author: Hamlet
License: GPLv3
Project-URL: Repository, https://github.com/hamlet-io/executor-python
Classifier: Natural Language :: English
Classifier: Intended Audience :: Developers
Classifier: Intended Audience :: System Administrators
Classifier: License :: OSI Approved :: GNU General Public License v3 (GPLv3)
Classifier: Programming Language :: Java
Classifier: Programming Language :: Python
Requires-Python: >=3.7
License-File: LICENSE
Requires-Dist: click <9.0.0,>=8.0.3
Requires-Dist: click-configfile <1.0.0,>=0.2.3
Requires-Dist: cookiecutter <3.0.0,>=2.1.1
Requires-Dist: tabulate <1.0.0,>=0.8.0
Requires-Dist: Jinja2 <4.0.0,>=3.0.3
Requires-Dist: jmespath <1.0.0,>=0.10.0
Requires-Dist: www-authenticate <1.0.0,>=0.9.2
Requires-Dist: httpx <1.0.0,>=0.21.2
Requires-Dist: marshmallow <4.0.0,>=3.7.0
Requires-Dist: dulwich <1.0.0,>=0.20.45
Requires-Dist: semver <3.0.0,>=2.13.0
Requires-Dist: importlib-resources <6.0.0,>=5.10.2
Requires-Dist: boto3 <2.0.0,>=1.20.0
Requires-Dist: botocore <2.0.0,>=1.20.0
Requires-Dist: fabric <3.0.0,>=2.6.0
Requires-Dist: simple-term-menu <2.0.0,>=1.4.1
Requires-Dist: docker <6.0.0,>=5.0.3
Requires-Dist: pytest <7.0.0,>=6.0.0
Requires-Dist: urllib3 <2
Provides-Extra: dev
Requires-Dist: coverage ; extra == 'dev'
Requires-Dist: freezegun ; extra == 'dev'
Requires-Dist: setuptools ; extra == 'dev'
Requires-Dist: flake8 ; extra == 'dev'
Requires-Dist: black ; extra == 'dev'
Requires-Dist: build ; extra == 'dev'
Requires-Dist: wheel ; extra == 'dev'
Requires-Dist: twine ; extra == 'dev'
Requires-Dist: Sphinx ; extra == 'dev'
Requires-Dist: sphinx-markdown-builder ; extra == 'dev'
Requires-Dist: sphinx-click ; extra == 'dev'
